biotree/__init__.py
biotree/smiles_to_target/__init__.py
biotree/smiles_to_target/chembal.py
biotree/utils/__init__.py
biotree/utils/decorator.py
babytree-0.2.0.dist-info/METADATA
babytree-0.2.0.dist-info/WHEEL
babytree-0.2.0.dist-info/RECORD
